pybumpver/__init__.py
pybumpver-0.1.0.dev0.dist-info/METADATA
pybumpver-0.1.0.dev0.dist-info/WHEEL
pybumpver-0.1.0.dev0.dist-info/licenses/AUTHORS.md
pybumpver-0.1.0.dev0.dist-info/licenses/LICENSE
pybumpver-0.1.0.dev0.dist-info/RECORD
